sbom_upload_validator/__init__.py
sbom_upload_validator/cli.py
sbom_upload_validator/config_cli.py
sbom_upload_validator/config_loader.py
sbom_upload_validator/dt_api_client.py
sbom_upload_validator/dt_api_utils.py
sbom_upload_validator/dt_config_loader.py
sbom_upload_validator/hierarchy_cli.py
sbom_upload_validator/hierarchy_manager.py
sbom_upload_validator/initialize_dt_hierarchy.py
sbom_upload_validator-1.1.4.dist-info/licenses/LICENSE
sbom_upload_validator-1.1.4.dist-info/METADATA
sbom_upload_validator-1.1.4.dist-info/WHEEL
sbom_upload_validator-1.1.4.dist-info/entry_points.txt
sbom_upload_validator-1.1.4.dist-info/top_level.txt
sbom_upload_validator-1.1.4.dist-info/RECORD
