Metadata-Version: 2.4
Name: sbom-upload-validator
Version: 1.1.4
Summary: Production-ready API for GitLab SBOM uploads to Dependency-Track with hierarchical management
Home-page: https://github.com/StL-Jim/sbom-upload-validator
Author: SBOM Upload Validator Project
Author-email: SBOM Upload Validator Project <sbom-validator@example.com>
License:                     GNU GENERAL PUBLIC LICENSE
Project-URL: Homepage, https://github.com/StL-Jim/sbom-upload-validator
Project-URL: Documentation, https://github.com/StL-Jim/sbom-upload-validator/blob/main/README.md
Project-URL: Repository, https://github.com/StL-Jim/sbom-upload-validator.git
Project-URL: Bug Reports, https://github.com/StL-Jim/sbom-upload-validator/issues
Project-URL: Docker Hub, https://hub.docker.com/r/stljim/sbom-upload-validator
Keywords: sbom,software-bill-of-materials,dependency-track,owasp,security,vulnerability,gitlab,cicd,federal,compliance
Classifier: Development Status :: 4 - Beta
Classifier: Intended Audience :: Developers
Classifier: Intended Audience :: System Administrators
Classifier: Intended Audience :: Information Technology
Classifier: License :: OSI Approved :: Apache Software License
Classifier: Operating System :: OS Independent
Classifier: Programming Language :: Python :: 3
Classifier: Programming Language :: Python :: 3.8
Classifier: Programming Language :: Python :: 3.9
Classifier: Programming Language :: Python :: 3.10
Classifier: Programming Language :: Python :: 3.11
Classifier: Programming Language :: Python :: 3.12
Classifier: Topic :: Security
Classifier: Topic :: Software Development :: Libraries :: Python Modules
Classifier: Topic :: System :: Systems Administration
Classifier: Topic :: Internet :: WWW/HTTP :: HTTP Servers
Classifier: Environment :: Web Environment
Classifier: Framework :: Flask
Requires-Python: >=3.8
License-File: LICENSE
Requires-Dist: Flask<4.0.0,>=2.3.0
Requires-Dist: requests<3.0.0,>=2.31.0
Requires-Dist: python-dotenv<2.0.0,>=1.0.0
Requires-Dist: PyYAML<7.0.0,>=6.0.0
Requires-Dist: Werkzeug<3.0.0,>=2.3.0
Provides-Extra: dev
Requires-Dist: pytest>=7.0.0; extra == "dev"
Requires-Dist: pytest-cov>=4.0.0; extra == "dev"
Requires-Dist: black>=23.0.0; extra == "dev"
Requires-Dist: flake8>=6.0.0; extra == "dev"
Requires-Dist: mypy>=1.0.0; extra == "dev"
Provides-Extra: docker
Requires-Dist: gunicorn>=21.0.0; extra == "docker"
Dynamic: author
Dynamic: home-page
Dynamic: license-file
Dynamic: requires-python
